setup.cfg
setup.py
coredata/__init__.py
coredata/coredata.py
coredata.egg-info/PKG-INFO
coredata.egg-info/SOURCES.txt
coredata.egg-info/dependency_links.txt
coredata.egg-info/requires.txt
coredata.egg-info/top_level.txt