Metadata-Version: 1.1
Name: coredata
Version: 0.1.5
Summary: A client to the Coredata API
Home-page: https://github.com/koddsson/coredata-python-client
Author: Kristján Oddsson
Author-email: koddsson@gmail.com
License: UNKNOWN
Download-URL: https://github.com/koddsson/coredata-python-client/tarball/0.1.5
Keywords: coredata
Platform: UNKNOWN
